Metadata-Version: 2.1
Name: visual-automata-demo
Version: 0.0.4
Summary: Visual Automata is a Python 3 library built as a wrapper for the Automata library to add more visualization features.
Home-page: https://github.com/lewiuberg/visual-automata-demo
Author: Lewi Lie Uberg
Author-email: lewi@uberg.me
License: MIT
Keywords: automata
Platform: UNKNOWN
Classifier: License :: OSI Approved :: MIT License
Classifier: Programming Language :: Python :: 3
Classifier: Programming Language :: Python :: 3.6
Requires-Dist: automata-lib
Requires-Dist: pandas
Requires-Dist: graphviz
Requires-Dist: colormath
Requires-Dist: jupyterlab
Requires-Dist: forbiddenfruit
